flowflow/__init__.py
flowflow-0.0.4.dist-info/WHEEL
flowflow-0.0.4.dist-info/METADATA
flowflow-0.0.4.dist-info/RECORD
